[{
  "_id": {
    "$oid": "661186aaff79497ea896f334"
  },
  "islemKodu": "TUPRS.E",
  "bultenAdi": "TUPRAS",
  "toplamIslemHacmi": 7190443253.7,
  "toplamİslemMiktari": 59530321
},
{
  "_id": {
    "$oid": "661186aaff79497ea896f335"
  },
  "islemKodu": "BIMAS.E",
  "bultenAdi": "BIM MAGAZALAR",
  "toplamIslemHacmi": 1737563787.3,
  "toplamİslemMiktari": 35579569
},
{
  "_id": {
    "$oid": "661186aaff79497ea896f336"
  },
  "islemKodu": "AEFES.E",
  "bultenAdi": "ANADOLU EFES",
  "toplamIslemHacmi": 444013142.94,
  "toplamİslemMiktari": 18123538
},
{
  "_id": {
    "$oid": "661186aaff79497ea896f337"
  },
  "islemKodu": "VESBE.E",
  "bultenAdi": "VESTEL BEYAZ ESYA",
  "toplamIslemHacmi": 94923047.82,
  "toplamİslemMiktari": 3787233
},
{
  "_id": {
    "$oid": "661186aaff79497ea896f338"
  },
  "islemKodu": "ULKER.E",
  "bultenAdi": "ULKER BISKUVI",
  "toplamIslemHacmi": 487954694.44,
  "toplamİslemMiktari": 20117534
},
{
  "_id": {
    "$oid": "661186aaff79497ea896f339"
  },
  "islemKodu": "KCHOL.E",
  "bultenAdi": "KOC HOLDING",
  "toplamIslemHacmi": 1669511921.6,
  "toplamİslemMiktari": 81294263
},
{
  "_id": {
    "$oid": "661186aaff79497ea896f33a"
  },
  "islemKodu": "TCELL.E",
  "bultenAdi": "TURKCELL",
  "toplamIslemHacmi": 3282959388.26,
  "toplamİslemMiktari": 229032151
},
{
  "_id": {
    "$oid": "661186aaff79497ea896f33b"
  },
  "islemKodu": "GARAN.E",
  "bultenAdi": "GARANTI BANKASI",
  "toplamIslemHacmi": 9343634502.93,
  "toplamİslemMiktari": 792784858
},
{
  "_id": {
    "$oid": "661186aaff79497ea896f33c"
  },
  "islemKodu": "SAHOL.E",
  "bultenAdi": "SABANCI HOLDING",
  "toplamIslemHacmi": 2464784884.01,
  "toplamİslemMiktari": 241151778
},
{
  "_id": {
    "$oid": "661186aaff79497ea896f33d"
  },
  "islemKodu": "EREGL.E",
  "bultenAdi": "EREGLI DEMIR CELIK",
  "toplamIslemHacmi": 5031425959.08,
  "toplamİslemMiktari": 536335414
},
{
  "_id": {
    "$oid": "661186aaff79497ea896f33e"
  },
  "islemKodu": "AKBNK.E",
  "bultenAdi": "AKBANK",
  "toplamIslemHacmi": 6294935228.2,
  "toplamİslemMiktari": 737210154
},
{
  "_id": {
    "$oid": "661186aaff79497ea896f33f"
  },
  "islemKodu": "ENJSA.E",
  "bultenAdi": "ENERJISA ENERJI",
  "toplamIslemHacmi": 483582298.43,
  "toplamİslemMiktari": 62294805
},
{
  "_id": {
    "$oid": "661186aaff79497ea896f340"
  },
  "islemKodu": "TTKOM.E",
  "bultenAdi": "TURK TELEKOM",
  "toplamIslemHacmi": 2354373012.9,
  "toplamİslemMiktari": 300454631
},
{
  "_id": {
    "$oid": "661186aaff79497ea896f341"
  },
  "islemKodu": "ISCTR.E",
  "bultenAdi": "IS BANKASI (C)",
  "toplamIslemHacmi": 4384462966.57,
  "toplamİslemMiktari": 637513640
},
{
  "_id": {
    "$oid": "661186aaff79497ea896f342"
  },
  "islemKodu": "ENKAI.E",
  "bultenAdi": "ENKA INSAAT",
  "toplamIslemHacmi": 272183209.26,
  "toplamİslemMiktari": 41353542
},
{
  "_id": {
    "$oid": "661186aaff79497ea896f343"
  },
  "islemKodu": "SISE.E",
  "bultenAdi": "SISE CAM",
  "toplamIslemHacmi": 9446107606.05,
  "toplamİslemMiktari": 1761095911
},
{
  "_id": {
    "$oid": "661186aaff79497ea896f344"
  },
  "islemKodu": "ISMEN.E",
  "bultenAdi": "IS Y. MEN. DEG.",
  "toplamIslemHacmi": 294986668.38,
  "toplamİslemMiktari": 61742533
},
{
  "_id": {
    "$oid": "661186aaff79497ea896f345"
  },
  "islemKodu": "GLYHO.E",
  "bultenAdi": "GLOBAL YAT. HOLDING",
  "toplamIslemHacmi": 466704917.26,
  "toplamİslemMiktari": 95671039
},
{
  "_id": {
    "$oid": "661186aaff79497ea896f346"
  },
  "islemKodu": "PEKGY.E",
  "bultenAdi": "PEKER GMYO",
  "toplamIslemHacmi": 412521418.63,
  "toplamİslemMiktari": 130323093
},
{
  "_id": {
    "$oid": "661186aaff79497ea896f347"
  },
  "islemKodu": "YKBNK.E",
  "bultenAdi": "YAPI VE KREDI BANK.",
  "toplamIslemHacmi": 4158929248.27,
  "toplamİslemMiktari": 1489694359
},
{
  "_id": {
    "$oid": "661186aaff79497ea896f348"
  },
  "islemKodu": "KRDMD.E",
  "bultenAdi": "KARDEMIR (D)",
  "toplamIslemHacmi": 14022872607.36,
  "toplamİslemMiktari": {
    "$numberLong": "4827282466"
  }
},
{
  "_id": {
    "$oid": "661186aaff79497ea896f349"
  },
  "islemKodu": "RTALB.E",
  "bultenAdi": "RTA LABORATUVARLARI",
  "toplamIslemHacmi": 318331916.67,
  "toplamİslemMiktari": 132720365
},
{
  "_id": {
    "$oid": "661186aaff79497ea896f34a"
  },
  "islemKodu": "EDIP.E",
  "bultenAdi": "EDIP GAYRIMENKUL",
  "toplamIslemHacmi": 173937818.71,
  "toplamİslemMiktari": 110511304
},
{
  "_id": {
    "$oid": "661186aaff79497ea896f34b"
  },
  "islemKodu": "ALBRK.E",
  "bultenAdi": "ALBARAKA TURK",
  "toplamIslemHacmi": 6460784369.69,
  "toplamİslemMiktari": {
    "$numberLong": "3847557161"
  }
},
{
  "_id": {
    "$oid": "661186aaff79497ea896f34c"
  },
  "islemKodu": "EKGYO.E",
  "bultenAdi": "EMLAK KONUT GMYO",
  "toplamIslemHacmi": 7454369164.06,
  "toplamİslemMiktari": {
    "$numberLong": "4705038293"
  }
},
{
  "_id": {
    "$oid": "661186aaff79497ea896f34d"
  },
  "islemKodu": "ARDYZ.E",
  "bultenAdi": "ARD BILISIM TEKNOLOJILERI",
  "toplamIslemHacmi": 1355051697.78,
  "toplamİslemMiktari": 97089354
},
{
  "_id": {
    "$oid": "661186aaff79497ea896f34e"
  },
  "islemKodu": "TURSG.E",
  "bultenAdi": "TURKIYE SIGORTA",
  "toplamIslemHacmi": 5729984499.66,
  "toplamİslemMiktari": 968263335
},
{
  "_id": {
    "$oid": "661186aaff79497ea896f34f"
  },
  "islemKodu": "QUAGR.E",
  "bultenAdi": "QUA GRANITE HAYAL YAPI",
  "toplamIslemHacmi": 3669863142.71,
  "toplamİslemMiktari": 145130753
},
{
  "_id": {
    "$oid": "661186aaff79497ea896f350"
  },
  "islemKodu": "BOBET.E",
  "bultenAdi": "BOGAZICI BETON SANAYI",
  "toplamIslemHacmi": 1349110521.23,
  "toplamİslemMiktari": 250519503
},
{
  "_id": {
    "$oid": "661186aaff79497ea896f351"
  },
  "islemKodu": "KZBGY.E",
  "bultenAdi": "KIZILBUK GYO",
  "toplamIslemHacmi": 2787887875.84,
  "toplamİslemMiktari": 144568279
},
{
  "_id": {
    "$oid": "661186aaff79497ea896f352"
  },
  "islemKodu": "KCAER.E",
  "bultenAdi": "KOCAER CELIK",
  "toplamIslemHacmi": 256216156.92,
  "toplamİslemMiktari": 9591862
},
{
  "_id": {
    "$oid": "661186aaff79497ea896f353"
  },
  "islemKodu": "EUREN.E",
  "bultenAdi": "EUROPEN ENDUSTRI",
  "toplamIslemHacmi": 2498031135.08,
  "toplamİslemMiktari": 104784887
},
{
  "_id": {
    "$oid": "661186aaff79497ea896f354"
  },
  "islemKodu": "SEGYO.E",
  "bultenAdi": "SEKER GMYO",
  "toplamIslemHacmi": 1651638416.42,
  "toplamİslemMiktari": 1392178085
},
{
  "_id": {
    "$oid": "661186aaff79497ea896f355"
  },
  "islemKodu": "ALTIN.S1",
  "bultenAdi": "DARPHANE ALTIN SERTIFIKASI",
  "toplamIslemHacmi": 548889042.57,
  "toplamİslemMiktari": 52044837
},
{
  "_id": {
    "$oid": "661186aaff79497ea896f356"
  },
  "islemKodu": "KTLEV.E",
  "bultenAdi": "KATILIMEVIM TAS. FIN.",
  "toplamIslemHacmi": 4500028685.31,
  "toplamİslemMiktari": 300714920
},
{
  "_id": {
    "$oid": "661186aaff79497ea896f357"
  },
  "islemKodu": "MHRGY.E",
  "bultenAdi": "MHR GMYO",
  "toplamIslemHacmi": 2792532056.79,
  "toplamİslemMiktari": 471471606
},
{
  "_id": {
    "$oid": "661186aaff79497ea896f358"
  },
  "islemKodu": "EKOS.E",
  "bultenAdi": "EKOS TEKNOLOJI",
  "toplamIslemHacmi": 194176823.54,
  "toplamİslemMiktari": 7947178
},
{
  "_id": {
    "$oid": "661186aaff79497ea896f359"
  },
  "islemKodu": "AGROT.E",
  "bultenAdi": "AGROTECH TEKNOLOJI",
  "toplamIslemHacmi": 941236721.06,
  "toplamİslemMiktari": 104488449
}]